<annotation>
	<folder>images</folder>
	<filename>0129.jpg</filename>
	<path>C:\Users\Timothy\PycharmProjects\Eye Tracking\models\images\0129.jpg</path>
	<source>
		<database>Unknown</database>
	</source>
	<size>
		<width>1280</width>
		<height>720</height>
		<depth>3</depth>
	</size>
	<segmented>0</segmented>
	<object>
		<name>eye</name>
		<pose>Unspecified</pose>
		<truncated>0</truncated>
		<difficult>0</difficult>
		<bndbox>
			<xmin>515</xmin>
			<ymin>433</ymin>
			<xmax>550</xmax>
			<ymax>454</ymax>
		</bndbox>
	</object>
	<object>
		<name>eye</name>
		<pose>Unspecified</pose>
		<truncated>0</truncated>
		<difficult>0</difficult>
		<bndbox>
			<xmin>682</xmin>
			<ymin>401</ymin>
			<xmax>715</xmax>
			<ymax>421</ymax>
		</bndbox>
	</object>
</annotation>
